hmathtools/__init__.py
hmathtools/hmt.py
hmathtools/setup.py
hmathtools-1.1.dist-info/LICENSE
hmathtools-1.1.dist-info/METADATA
hmathtools-1.1.dist-info/WHEEL
hmathtools-1.1.dist-info/top_level.txt
hmathtools-1.1.dist-info/RECORD
