Metadata-Version: 2.1
Name: hmathtools
Version: 1.1
Summary: A simple package that uses NumPy .
Home-page: https://github.com/your_username/my_package
Author: Harman Singh
Author-email: the.programming.hacker.hk+1@gmail.com
Classifier: Programming Language :: Python :: 3
Classifier: License :: OSI Approved :: MIT License
Requires-Python: >=3.10
License-File: LICENSE
Requires-Dist: numpy
